code_audit_23/__init__.py
code_audit_23/gitignore_utils.py
code_audit_23/logger.py
code_audit_23/main.py
code_audit_23/semgrep_cli.py
code_audit_23/sonarqube_cli.py
code_audit_23/sonarqube_dotnet.py
code_audit_23/sonarqube_java.py
code_audit_23/trivy_cli.py
code_audit_23/sonar-scanner/bin/sonar-scanner
code_audit_23/sonar-scanner/bin/sonar-scanner-debug
code_audit_23/sonar-scanner/bin/sonar-scanner-debug.bat
code_audit_23/sonar-scanner/bin/sonar-scanner.bat
code_audit_23/sonar-scanner/conf/sonar-scanner.properties
code_audit_23/sonar-scanner/lib/sonar-scanner-cli-7.3.0.5189.jar
code_audit_23-0.1.15.dist-info/licenses/LICENSE
code_audit_23-0.1.15.dist-info/METADATA
code_audit_23-0.1.15.dist-info/WHEEL
code_audit_23-0.1.15.dist-info/entry_points.txt
code_audit_23-0.1.15.dist-info/top_level.txt
code_audit_23-0.1.15.dist-info/RECORD
