Metadata-Version: 2.4
Name: code-audit-23
Version: 0.1.15
Summary: A simple local scanner for code audits (Trivy, Semgrep, SonarQube, for Brain Station 23)
Author-email: Ahmad Al-Sajid <ahmad.sajid@brainstation23.com>
License-Expression: MIT
Requires-Python: <3.14,>=3.10
License-File: LICENSE
Requires-Dist: click<9.0,>=8.1.7
Requires-Dist: python-dotenv<2.0,>=1.0
Requires-Dist: requests<3.0,>=2.31
Requires-Dist: semgrep<2.0,>=1.0
Requires-Dist: tomli<3.0,>=2.0.1
Dynamic: license-file
